xibs/__init__.py
xibs/_old_michalis.py
xibs/analytical.py
xibs/dispatch.py
xibs/formulary.py
xibs/inputs.py
xibs/kicks.py
xibs/version.py
xibs-0.7.1.dist-info/METADATA
xibs-0.7.1.dist-info/WHEEL
xibs-0.7.1.dist-info/licenses/LICENSE
xibs-0.7.1.dist-info/RECORD
